braintree-stubs/METADATA.toml
braintree-stubs/__init__.pyi
braintree-stubs/account_updater_daily_report.pyi
braintree-stubs/ach_mandate.pyi
braintree-stubs/add_on.pyi
braintree-stubs/add_on_gateway.pyi
braintree-stubs/address.pyi
braintree-stubs/address_gateway.pyi
braintree-stubs/amex_express_checkout_card.pyi
braintree-stubs/android_pay_card.pyi
braintree-stubs/apple_pay_card.pyi
braintree-stubs/apple_pay_gateway.pyi
braintree-stubs/apple_pay_options.pyi
braintree-stubs/attribute_getter.pyi
braintree-stubs/authorization_adjustment.pyi
braintree-stubs/bank_account_instant_verification_gateway.pyi
braintree-stubs/bank_account_instant_verification_jwt.pyi
braintree-stubs/bank_account_instant_verification_jwt_request.pyi
braintree-stubs/bin_data.pyi
braintree-stubs/blik_alias.pyi
braintree-stubs/braintree_gateway.pyi
braintree-stubs/client_token.pyi
braintree-stubs/client_token_gateway.pyi
braintree-stubs/configuration.pyi
braintree-stubs/connected_merchant_paypal_status_changed.pyi
braintree-stubs/connected_merchant_status_transitioned.pyi
braintree-stubs/credentials_parser.pyi
braintree-stubs/credit_card.pyi
braintree-stubs/credit_card_gateway.pyi
braintree-stubs/credit_card_verification.pyi
braintree-stubs/credit_card_verification_gateway.pyi
braintree-stubs/credit_card_verification_search.pyi
braintree-stubs/customer.pyi
braintree-stubs/customer_gateway.pyi
braintree-stubs/customer_search.pyi
braintree-stubs/customer_session_gateway.pyi
braintree-stubs/descriptor.pyi
braintree-stubs/disbursement.pyi
braintree-stubs/disbursement_detail.pyi
braintree-stubs/discount.pyi
braintree-stubs/discount_gateway.pyi
braintree-stubs/dispute.pyi
braintree-stubs/dispute_gateway.pyi
braintree-stubs/dispute_search.pyi
braintree-stubs/document_upload.pyi
braintree-stubs/document_upload_gateway.pyi
braintree-stubs/enriched_customer_data.pyi
braintree-stubs/environment.pyi
braintree-stubs/error_codes.pyi
braintree-stubs/error_result.pyi
braintree-stubs/errors.pyi
types_braintree-4.40.0.20251025.dist-info/licenses/LICENSE
types_braintree-4.40.0.20251025.dist-info/METADATA
types_braintree-4.40.0.20251025.dist-info/WHEEL
types_braintree-4.40.0.20251025.dist-info/top_level.txt
types_braintree-4.40.0.20251025.dist-info/RECORD
